bluesteam/__init__.py
bluesteam/bluesteam_biorefineries/__init__.py
bluesteam/bluesteam_biorefineries/generic/__init__.py
bluesteam/bluesteam_biorefineries/generic/_bluestea.py
bluesteam/bluesteam_biorefineries/generic/_chemicals.py
bluesteam/bluesteam_biorefineries/generic/_process_settings.py
bluesteam/bluesteam_biorefineries/generic/_system.py
bluesteam/bluesteam_biorefineries/generic/_tea.py
bluesteam/bluesteam_biorefineries/generic/example_runs.py
bluesteam/bluesteam_biorefineries/generic/load_generic.py
bluesteam/bluesteam_biorefineries/generic/units.py
bluesteam/bluesteam_biorefineries/generic/utils.py
bluesteam/separability_tools/__init__.py
bluesteam/separability_tools/bluesteam_separability_results_2022.9.23-12.42.xlsx
bluesteam/separability_tools/estimate_separability.py
bluesteam/separability_tools/utils.py
bluesteam-0.0.6.dist-info/LICENSE.txt
bluesteam-0.0.6.dist-info/METADATA
bluesteam-0.0.6.dist-info/WHEEL
bluesteam-0.0.6.dist-info/top_level.txt
bluesteam-0.0.6.dist-info/RECORD
