Metadata-Version: 2.1
Name: bluesteam
Version: 0.0.6
Summary: Bluestem leverages AutoSynthesis, BioSTEAM, and biorefineries in BioIndustrial-Park for automated process synthesis and design of biorefineries.
Home-page: https://github.com/BluestemBiosciences/bluesteam
Author: Sarang S. Bhagwat
Author-email: sarang.bhagwat.git@gmail.com
License: MIT
Classifier: Development Status :: 3 - Alpha
Classifier: Intended Audience :: Science/Research
Classifier: License :: OSI Approved :: University of Illinois/NCSA Open Source License
Classifier: Operating System :: Microsoft :: Windows
Classifier: Programming Language :: Python :: 3.9
License-File: LICENSE.txt
Requires-Dist: biorefineries (==2.23.18)
Requires-Dist: autosynthesis (==0.0.17)
